MANIFEST.in
README.rst
setup.cfg
setup.py
importtools/__init__.py
importtools/datasets.py
importtools/importables.py
importtools/loaders.py
importtools/sync.py
importtools.egg-info/PKG-INFO
importtools.egg-info/SOURCES.txt
importtools.egg-info/dependency_links.txt
importtools.egg-info/top_level.txt