Metadata-Version: 1.0
Name: importtools
Version: 0.1.5
Summary: Import tools for various data sets.
Home-page: https://github.com/pbs/importtools
Author: Sever Banesiu
Author-email: banesiu.sever@gmail.com
License: UNKNOWN
Platform: UNKNOWN
